{
  "phrases": [
    {
      "phrase": "de-",
      "hanja": "",
      "example": {},
      "meanings": [
        "Prefix <‘…의 반대의, 반[역]–’의 뜻을 나타냄>",
        "Prefix <‘분리·제거’의 뜻을 나타냄>"
      ]
    },
    {
      "phrase": "de",
      "hanja": "",
      "example": {},
      "meanings": [
        "Preposition […에서[부터], …에 대하여]의 뜻"
      ]
    },
    {
      "phrase": "de",
      "hanja": "",
      "example": {},
      "meanings": [
        "Preposition […의, …에서, …에 속하는]의 뜻"
      ]
    },
    {
      "phrase": "DE",
      "hanja": "",
      "example": {},
      "meanings": [
        "[미] [우편] Delaware, [미해군] destroyer escort"
      ]
    },
    {
      "phrase": "D.E.",
      "hanja": "",
      "example": {},
      "meanings": [
        "defensive end, Doctor of Engineering, driver education"
      ]
    }
  ],
  "meanings": [
    {
      "meaning": "Drift Error",
      "frequency": 0
    },
    {
      "meaning": "des-",
      "frequency": 0
    },
    {
      "meaning": "-데",
      "frequency": 0
    },
    {
      "meaning": "Directed Energy",
      "frequency": 0
    },
    {
      "meaning": "Discrete Event",
      "frequency": 0
    }
  ],
  "vlive": [
    {
      "korean": "나만의 힐링 방법은? How do you de-stress? 듣기 View video OSEN : Golden Child 골든차일드의 찐텐션, 먹는 것만 봐도 흐뭇 #스타로드 08",
      "english": "How do you de-stress?"
    },
    {
      "korean": "다음 문제는 장준의 스트레스 해소법은? How does JANG JUN de-stress? 듣기 View video OSEN : Golden Child 골든차일드 재현, 얼굴 중 가장 자신있는 곳은? #스타로드 03",
      "english": "How does JANG JUN de-stress?"
    },
    {
      "korean": "장준이의 스트레스 해소법은 하나 둘 셋! What do I do to de-stress? 1, 2, 3! 듣기 View video OSEN : Golden Child 골든차일드 재현, 얼굴 중 가장 자신있는 곳은? #스타로드 03",
      "english": "What do I do to de-stress? 1, 2, 3!"
    },
    {
      "korean": "데 - 그래서? De. - So? 듣기 View video TWICE : 나모사",
      "english": "De. - So?"
    },
    {
      "korean": "너도 '데'야? You are with \"de\" too? 듣기 View video TWICE : 나모사",
      "english": "You are with \"de\" too?"
    }
  ],
  "examples": [
    {
      "korean": "He held power de jure and de facto. 발음듣기 그는 법률적으로도 또 사실적으로도 권력을 쥐고 있었다. Oxford Advanced Learner's English-Korean Dictionary",
      "english": "He held power de jure and de facto. 발음"
    },
    {
      "korean": "Evening dress is de rigueur at the casino. 발음듣기 그 카지노에서는 정장이 필요하다[정장을 해야 한다]. Oxford Advanced Learner's English-Korean Dictionary",
      "english": "Evening dress is de rigueur at the casino. 발음"
    },
    {
      "korean": "This school takes only the crème de la crème. 발음듣기 이 학교에서는 우수한 학생들 중에서도 우수한 학생들만 받습니다. Oxford Advanced Learner's English-Korean Dictionary",
      "english": "This school takes only the crème de la crème. 발음"
    },
    {
      "korean": "The general took de facto control of the country. 발음듣기 그 장군이 그 나라의 실질적인 통치권을 쥐고 있었다. Oxford Advanced Learner's English-Korean Dictionary",
      "english": "The general took de facto control of the country. 발음"
    },
    {
      "korean": "There is a de luxe model available, but it’ll cost you. 발음듣기 디럭스 모델도 나와 있지만 값이 비쌀 거예요. Oxford Advanced Learner's English-Korean Dictionary",
      "english": "There is a de luxe model available, but it’ll cost you. 발음"
    }
  ]
}