{
  "phrases": [
    {
      "phrase": "네",
      "hanja": "",
      "example": {},
      "meanings": [
        "(긍정의 대답) yes",
        "(반문하는 말) pardon (me), (S) what"
      ]
    },
    {
      "phrase": "네",
      "hanja": "",
      "example": {},
      "meanings": [
        "Determiner four (→넉)"
      ]
    },
    {
      "phrase": "네",
      "hanja": "",
      "example": {},
      "meanings": [
        "Pronoun ne"
      ]
    },
    {
      "phrase": "네",
      "hanja": "",
      "example": {},
      "meanings": [
        "ne (→내)"
      ]
    },
    {
      "phrase": "내[네] 깐에는",
      "hanja": "",
      "example": {},
      "meanings": [
        "by my[your] account"
      ]
    }
  ],
  "meanings": [
    {
      "meaning": "yes",
      "frequency": 3
    },
    {
      "meaning": "eh",
      "frequency": 3
    },
    {
      "meaning": "OK",
      "frequency": 3
    },
    {
      "meaning": "thank you",
      "frequency": 3
    },
    {
      "meaning": "thanks",
      "frequency": 3
    }
  ],
  "vlive": [
    {
      "korean": "네? - 네? Huh? - Huh? 듣기 View video BTS : [Full] BTS Comeback Special: '보'이는 '라'이브 '해'요",
      "english": "Huh? - Huh?"
    },
    {
      "korean": "왜죠? - 네? Why? - Sorry? 듣기 View video NU'EST : [NU'EST] L.O.Λ.E STORY EP.19 뉴이스트의 2020 왁자지껄 운수대통 #1",
      "english": "Why? - Sorry?"
    },
    {
      "korean": "네? - 네? - 태백? Huh? - Huh? - Taebaek? 듣기 View video BTS : [Full] BTS Comeback Special: '보'이는 '라'이브 '해'요",
      "english": "Huh? - Huh? - Taebaek?"
    },
    {
      "korean": "웬일이야 네가? What's going on? 듣기 View video 플레이리스트 (Playlist) : 마지막화) 5분 만에 전남친한테 최고의 복수하는 법 [엑스엑스(XX)] - EP.10",
      "english": "What's going on?"
    },
    {
      "korean": "조용히 해! - 네! Be quiet. - Yes. 듣기 View video Stray Kids : 산을 넘어 산호세로 ~~❤",
      "english": "Be quiet. - Yes."
    }
  ],
  "examples": [
    {
      "korean": "I am the youngest of four sisters. 듣기 Add to Wordbook 나는 네 자매 중 막내이다. Oxford Advanced Learner's English-Korean Dictionary",
      "english": "I am the youngest of four sisters. Add to Wordbook"
    },
    {
      "korean": "Just whack your bags in the corner. 듣기 Add to Wordbook 네 가방들은 그냥 구석에 던져 놔. Oxford Advanced Learner's English-Korean Dictionary",
      "english": "Just whack your bags in the corner. Add to Wordbook"
    },
    {
      "korean": "The board is available in four thicknesses. 듣기 Add to Wordbook 그 판자는 네 가지 두께로 나온다. Oxford Advanced Learner's English-Korean Dictionary",
      "english": "The board is available in four thicknesses. Add to Wordbook"
    },
    {
      "korean": "How did you get that bump on your forehead? 듣기 Add to Wordbook 네 이마에 그 혹은 어쩌다 생긴 거니? Oxford Advanced Learner's English-Korean Dictionary",
      "english": "How did you get that bump on your forehead? Add to Wordbook"
    },
    {
      "korean": "He cut four thick slices from the loaf. 듣기 Add to Wordbook 그가 빵 덩어리에서 두툼하게 네 조각을 잘라 내었다. Oxford Advanced Learner's English-Korean Dictionary",
      "english": "He cut four thick slices from the loaf. Add to Wordbook"
    }
  ]
}