{
  "phrases": [
    {
      "phrase": "먹다",
      "hanja": "",
      "example": {},
      "meanings": [
        "(음식을) eat, have, (formal) consume, (약 등을) take, (빨리) devour",
        "take, (뇌물·이익 등을) get",
        "(나이를) get older, grow older"
      ]
    },
    {
      "phrase": "먹다",
      "hanja": "",
      "example": {},
      "meanings": [
        "Verb be deaf (→처먹다)"
      ]
    },
    {
      "phrase": "먹다",
      "hanja": "",
      "example": {},
      "meanings": [
        "Assistant adverb meokda"
      ]
    },
    {
      "phrase": "먹고 떨어지다",
      "hanja": "",
      "example": {},
      "meanings": [
        "eat and fall off",
        "eat and fall off"
      ]
    },
    {
      "phrase": "먹고 들어가다",
      "hanja": "",
      "example": {},
      "meanings": [
        "eat and go into"
      ]
    }
  ],
  "meanings": [
    {
      "meaning": "under one's[the] belt",
      "frequency": 0
    },
    {
      "meaning": "live on something",
      "frequency": 0
    },
    {
      "meaning": "feed on/off something",
      "frequency": 0
    },
    {
      "meaning": "subsist",
      "frequency": 3
    },
    {
      "meaning": "orgy",
      "frequency": 3
    }
  ],
  "vlive": [
    {
      "korean": "먹고 싶어? Do you want to eat it? 듣기 View video AB6IX : 영민이의 '몰래라이브 #1'",
      "english": "Do you want to eat it?"
    },
    {
      "korean": "[먹고 있어?] [Are you eating now?] View video TWICE : 트와이스 복자매 나모의 “도전! ASMR” EP.01",
      "english": "[Are you eating now?]"
    },
    {
      "korean": "이거 먹고 저리 가! Take this and go! 듣기 View video 콬TV (WHYNOT) : 전생 체험하다가 죽음을 경험한 로켓펀치 연희 #아이돌 #리얼리티 ┃로켓펀치 [펀치타임",
      "english": "Take this and go!"
    },
    {
      "korean": "잠깐... 먹고 있어? Wait. Are you eating now? 듣기 View video TWICE : 트와이스 복자매 나모의 “도전! ASMR” EP.01",
      "english": "Wait. Are you eating now?"
    },
    {
      "korean": "간식 먹고 싶어? Do you want to eat a snack? 듣기 View video AB6IX : 영민이의 '몰래라이브 #1'",
      "english": "Do you want to eat a snack?"
    }
  ],
  "examples": [
    {
      "korean": "whales that feed deep beneath the waves 듣기 Add to Wordbook 바다 깊은 곳에서 먹이를 먹고 사는 고래들 Oxford Advanced Learner's English-Korean Dictionary",
      "english": "whales that feed deep beneath the waves Add to Wordbook"
    },
    {
      "korean": "Do you find that onions repeat on you? 듣기 Add to Wordbook 당신은 양파를 먹고 나면 속에서 받치나요? Oxford Advanced Learner's English-Korean Dictionary",
      "english": "Do you find that onions repeat on you? Add to Wordbook"
    },
    {
      "korean": "She had no stomach for the leftover stew. 듣기 Add to Wordbook 그녀는 남은 스튜를 먹고 싶지 않았다. Oxford Advanced Learner's English-Korean Dictionary",
      "english": "She had no stomach for the leftover stew. Add to Wordbook"
    },
    {
      "korean": "He sat at the table stuffing himself. 듣기 Add to Wordbook 그는 식탁에 앉아 음식을 잔뜩 먹고 있었다. Oxford Advanced Learner's English-Korean Dictionary",
      "english": "He sat at the table stuffing himself. Add to Wordbook"
    },
    {
      "korean": "He steeled himself to tell them the truth. 듣기 Add to Wordbook 그는 마음을 단단히 먹고 그들에게 진실을 말했다. Oxford Advanced Learner's English-Korean Dictionary",
      "english": "He steeled himself to tell them the truth. Add to Wordbook"
    }
  ]
}