{
  "phrases": [
    {
      "phrase": "애새끼",
      "hanja": "",
      "example": {},
      "meanings": [
        "a child"
      ]
    }
  ],
  "meanings": [
    {
      "meaning": "perisher",
      "frequency": 0
    },
    {
      "meaning": "brat",
      "frequency": 3
    },
    {
      "meaning": "a spoiled brat",
      "frequency": 0
    },
    {
      "meaning": "He's an arrogant little swine!",
      "frequency": 0
    },
    {
      "meaning": "a snivelling little brat",
      "frequency": 0
    }
  ],
  "vlive": [
    {
      "korean": "아니 내 말은... - 애새끼 흉내는 그만할 때 안 됐냐? No I was just... - Aren't you too old to be acting like a little kid? 듣기 View video 콬TV (WHYNOT) : 네 옆에는 늘 내가 있을래 [연애미수] EP10",
      "english": "No I was just... - Aren't you too old to be acting like a little kid?"
    }
  ],
  "examples": [
    {
      "korean": "a snivelling little brat 듣기 Add to Wordbook 자꾸 울며 보채는 애새끼 Oxford Advanced Learner's English-Korean Dictionary",
      "english": "a snivelling little brat Add to Wordbook"
    },
    {
      "korean": "Come here, you little bugger! 듣기 Add to Wordbook 이리 와, 이 애새끼야! Oxford Advanced Learner's English-Korean Dictionary",
      "english": "Come here, you little bugger! Add to Wordbook"
    },
    {
      "korean": "He’s a nasty little creep! 듣기 Add to Wordbook 걔는 정말 소름끼치는 애 새끼야! Oxford Advanced Learner's English-Korean Dictionary",
      "english": "He’s a nasty little creep! Add to Wordbook"
    },
    {
      "korean": "He’s an arrogant little swine! 듣기 Add to Wordbook 그는 거만한 애새끼야! Oxford Advanced Learner's English-Korean Dictionary",
      "english": "He’s an arrogant little swine! Add to Wordbook"
    },
    {
      "korean": "a spoiled/spoilt brat 듣기 Add to Wordbook 제멋대로 큰/버르장머리 없는 애새끼 Oxford Advanced Learner's English-Korean Dictionary",
      "english": "a spoiled/spoilt brat Add to Wordbook"
    }
  ]
}