{
  "phrases": [
    {
      "phrase": "초반",
      "hanja": " (初盤)",
      "example": {},
      "meanings": [
        "(경기·선거 등의) early phase, early stage",
        "(일정한 기간의 처음 단계)"
      ]
    },
    {
      "phrase": "1990년대 초반에",
      "hanja": "",
      "example": {},
      "meanings": [
        "in the early 1990s"
      ]
    },
    {
      "phrase": "오십 대 초반[중반; 후반]",
      "hanja": "",
      "example": {},
      "meanings": [
        "early[mid-, late] fifties"
      ]
    },
    {
      "phrase": "30대 초반입니다.",
      "hanja": "",
      "example": {},
      "meanings": [
        "실용회화-데이트 I'm in my early thirties."
      ]
    },
    {
      "phrase": "21세기 초반의 양상",
      "hanja": "",
      "example": {},
      "meanings": [
        "Early Phase's Aspect in 21st Century"
      ]
    }
  ],
  "meanings": [
    {
      "meaning": "beginning",
      "frequency": 3
    },
    {
      "meaning": "tween",
      "frequency": 0
    },
    {
      "meaning": "pre-teen",
      "frequency": 0
    },
    {
      "meaning": "first blood",
      "frequency": 0
    },
    {
      "meaning": "early[late] teens",
      "frequency": 0
    }
  ],
  "vlive": [
    {
      "korean": "초반에 뭐 긴장할 필요가 있어? There's no need to be nervous at the beginning. 듣기 View video NU'EST : [NU'EST] L.O.Λ.E STORY EP.19 뉴이스트의 2020 왁자지껄 운수대통 #1",
      "english": "There's no need to be nervous at the beginning."
    },
    {
      "korean": "나 진짜 잘 한 줄 알았어 - 초반에 잘 했어 - 대형은 근데 진짜... I thought I did a good job. - You did well in the beginning. 듣기 View video OSEN : PENTAGON 펜타곤, 벌칙의 주인공은? (ft.애교의 늪) #스타로드 02",
      "english": "I thought I did a good job. - You did well in the beginning."
    },
    {
      "korean": "초반에 말이 많았는데 중간쯤 지나면서 약간... He talked a lot in the beginning, but now... 듣기 View video SEVENTEEN : [GOING SEVENTEEN 2020] EP.3 돈't Lie #1 (Don't Lie #1)",
      "english": "He talked a lot in the beginning, but now..."
    },
    {
      "korean": "19살 초반에 와 벌써? Early 19... Wow, already?? 듣기 View video AB6IX : 오늘도 행복한 하루 보내셨나용?❤",
      "english": "Early 19... Wow, already??"
    },
    {
      "korean": "전? 19살 때 딱... 아니 18살 초반? 아닌데? 19살 초반인가? I was 19... Or early 18? No? Early 19? 듣기 View video AB6IX : 오늘도 행복한 하루 보내셨나용?❤",
      "english": "I was 19... Or early 18? No? Early 19?"
    }
  ],
  "examples": [
    {
      "korean": "The team failed to capitalize on their early lead. 듣기 Add to Wordbook 그 팀은 초반의 주도권을 활용하지 못했다. Oxford Advanced Learner's English-Korean Dictionary",
      "english": "The team failed to capitalize on their early lead. Add to Wordbook"
    },
    {
      "korean": "a pleasant woman in early/late middle age 듣기 Add to Wordbook 중년기 초반/후반의 쾌활한 여성 Oxford Advanced Learner's English-Korean Dictionary",
      "english": "a pleasant woman in early/late middle age Add to Wordbook"
    },
    {
      "korean": "The dollar staged a recovery earlier today. 듣기 Add to Wordbook 오늘 초반에는 달러가 회복세를 보였다. Oxford Advanced Learner's English-Korean Dictionary",
      "english": "The dollar staged a recovery earlier today. Add to Wordbook"
    },
    {
      "korean": "He did a stint abroad early in his career. 듣기 Add to Wordbook 그는 경력 초반에 해외 근무를 했다. Oxford Advanced Learner's English-Korean Dictionary",
      "english": "He did a stint abroad early in his career. Add to Wordbook"
    },
    {
      "korean": "Manchester lost their early two-goal lead. 듣기 Add to Wordbook 맨체스터가 초반의 두 골 우위를 상실했다. Oxford Advanced Learner's English-Korean Dictionary",
      "english": "Manchester lost their early two-goal lead. Add to Wordbook"
    }
  ]
}