{
  "phrases": [
    {
      "phrase": "헤",
      "hanja": "",
      "example": {},
      "meanings": [
        "(입을 벌린 모양)"
      ]
    },
    {
      "phrase": "heh",
      "hanja": "",
      "example": {},
      "meanings": [
        "Interjection 쳇, 허허, 엣 ((경멸·가소로움·놀람·반문 등의 소리))"
      ]
    },
    {
      "phrase": "hae",
      "hanja": "",
      "example": {},
      "meanings": [
        "Transitive verb, Modal verb 스코 HAVE의 1·2인칭 단수·복수 현재"
      ]
    },
    {
      "phrase": "H.E.H.",
      "hanja": "",
      "example": {},
      "meanings": [
        "His[Her] Exalted Highness"
      ]
    },
    {
      "phrase": "heh",
      "hanja": "",
      "example": {},
      "meanings": [
        "Noun HE3"
      ]
    }
  ],
  "meanings": [
    {
      "meaning": "heh deity",
      "frequency": 0
    },
    {
      "meaning": "burrow(=stray) in the dark",
      "frequency": 0
    },
    {
      "meaning": "Terug naar Oegstgeest",
      "frequency": 0
    },
    {
      "meaning": "Abraham Joshua Heschel",
      "frequency": 0
    },
    {
      "meaning": "tetrahedricity",
      "frequency": 0
    }
  ],
  "vlive": [
    {
      "korean": "헤. 메. 스 그리고 오센과 함께 - 혹시 여러분들 먹고 싶은 거 있나요? Ha, Me, S, and with OSEN. - Is there anything you want to have? 듣기 View video OSEN : MONSTA X 몬스타엑스 'Star Road' EP.02",
      "english": "Ha, Me, S, and with OSEN. - Is there anything you want to have?"
    },
    {
      "korean": "헤~ 정말 빠르구먼 - 36, 37! You are very fast! - 36, 37! 듣기 View video Stray Kids : [Two Kids Room(투키즈룸)] VOL.2 Ep.05 방찬 X 현진",
      "english": "You are very fast! - 36, 37!"
    },
    {
      "korean": "[(정한이 형한테 뭐라 하지 마!)] 헤 헤 헤이! [(Don't talk like that to Jeonghan!)] Hey!! 듣기 View video SEVENTEEN : [SEVENTEEN] GOING SEVENTEEN SPIN-OFF EP.24 2018 연말 특집",
      "english": "[(Don't talk like that to Jeonghan!)] Hey!!"
    },
    {
      "korean": "[나도 먹을래] 헤~에! 맛있겠다! 야 먹을까봐. [I want it too...] It looks delicious. I should have it too. 듣기 View video 모해 MOHAE : [WekiMeki 위키미키 모해?] EP43 어서 와! 방콕은 처음이지?",
      "english": "[I want it too...] It looks delicious. I should have it too."
    },
    {
      "korean": "하,헤,히,호,후! Ha, he, hi, ho, hu! 듣기 View video BRANDNEW MUSIC : 강민희의 뷰티톡톡! (세미 스모키 메이크업편)",
      "english": "Ha, he, hi, ho, hu!"
    }
  ],
  "examples": [
    {
      "korean": "She was staring into space, her mouth slack. 듣기 Add to Wordbook 그녀는 입을 헤 벌린 채 허공을 응시하고 있었다. Oxford Advanced Learner's English-Korean Dictionary",
      "english": "She was staring into space, her mouth slack. Add to Wordbook"
    },
    {
      "korean": "He stared at her with his mouth wide open[agape]. 듣기 Add to Wordbook 그는 입을 헤 벌리고 그녀를 쳐다보았다 Neungyule",
      "english": "He stared at her with his mouth wide open[agape]. Add to Wordbook"
    },
    {
      "korean": "Don't stand round gaping. 듣기 Add to Wordbook (바보같이) 입을 헤 벌리고 서 있지 마. Friendict Level English-Korean Dictionary",
      "english": "Don't stand round gaping. Add to Wordbook"
    },
    {
      "korean": "He was sleeping with his mouth wide open. 듣기 Add to Wordbook 그는 입을 헤 벌리고 자고 있었다 Neungyule",
      "english": "He was sleeping with his mouth wide open. Add to Wordbook"
    },
    {
      "korean": "Producer David Heyman of the fourth in the series said, 'It's probably not for 4-year-olds.' 듣기 Add to Wordbook 이 네번째 시리즈의 제작자 데이빗 헤 이먼은'이는 아마도 4살의 아이들을 위한 것은 아니다'라 고 말했다. Neungyule",
      "english": "Producer David Heyman of the fourth in the series said, 'It's probably not for 4-year-olds.' Add to Wordbook"
    }
  ]
}