{
  "phrases": [],
  "meanings": [
    {
      "meaning": "he 2",
      "frequency": 0
    },
    {
      "meaning": "hee",
      "frequency": 0
    }
  ],
  "vlive": [
    {
      "korean": "봤어? 미안 히히히 - 왜? 뭐래? Did you see? Sorry, hehe. - Why? What is she saying? 듣기 View video 플레이리스트 (Playlist) : 선공개)) 구남친이 던진 말 무슨 뜻임? [웹시트콤 한입만 시즌2] - EP.06",
      "english": "Did you see? Sorry, hehe. - Why? What is she saying?"
    },
    {
      "korean": "[BOBBY 흥폭발] 이히히히히히히히히히~ [Bobby is exploding with excitement] Heheheheheheh. 듣기 View video iKON : iKON - ‘자체제작 iKON TV’ EP.6-1",
      "english": "[Bobby is exploding with excitement] Heheheheheheh."
    },
    {
      "korean": "['김다현' 씨 주문 제작 상품 생산 중] [히히히 내 목도리!] 이번에 우리 김다현 씨가 특별 주문하셨어요. [Hehehe! My scarf!] Kim Dahyun made a special order for this. 듣기 View video TWICE : TWICE TV 2018 EP.03",
      "english": "[Hehehe! My scarf!] Kim Dahyun made a special order for this."
    }
  ],
  "examples": []
}